{"data":[[{"name":"empCode","value":"39"},{"name":"fullName","value":"Siddhesh"},{"name":"lastName","value":"Thakur"},{"name":"gender","value":"male"},{"name":"email","value":"siddhesh_thakur47@gmail.com"},{"name":"phone","value":"9892125742"},{"name":"salary","value":"100000"},{"name":"city","value":"Ulwe"}],[{"name":"empCode","value":"84"},{"name":"fullName","value":"Shivani"},{"name":"lastName","value":"Mhatre"},{"name":"gender","value":"Female"},{"name":"email","value":"shivan_thakur47@hmail.com"},{"name":"phone","value":"8097155154"},{"name":"salary","value":"200000"},{"name":"city","value":"Mumbai"}]]}